{
  
      
     
      "title": "Barbie y las estrellas de rock",
      "description": "La historia está basada en la línea de muñecas Barbie y las Rockeras, que incluía a Barbie como la líder de una banda. El especial se emitió originalmente como una mini-serie de dos partes con una duración aproximada cada tramo de 25 minutos. La segunda parte se tituló Barbie de regreso a la Tierra.",
      "director": "Bernard Deyriès",
      "producer": "Andy Heyward",
      "poster": "",
      "release_date": "1986",
      "duration": "50",
      "people": [
      

        {
          "id": "",
          "name": "Barbie",
          "img": " ",
          "gender": "female",
          "age": "?",
          "eye_color": "blue",
          "hair_color": "blond",
          "specie": "Human",

        },

        {

          "id": "",
          "name": "Ken",
          "img": " ",
          "gender": "male",
          "age": "26",
          "eye_color": "blue ",
          "hair_color": " blond",
          "specie": "Human",


        }

      ]
    
    }



    {
        "id": "",
      "title": "Barbie y las sensaciones:devuelta a la tierra",
      "description": "Después del primer gran concierto por la paz en el espacio, Barbie y su banda Las sensaciones van a volver a casa. Durante el viaje de regreso a la tierra, en el transbordador espacial, comienzan a tocar una canción (Rockeando Devuelta), pocos segundos después, un túnel del tiempo se está formando frente a la nave.",
      "director": "Bernard Deyriès",
      "producer": "Andy Heyward",
      "poster": 
       "",
      "release_date": "1987",
      "duration":"50",
      "people":

      
        "id": "",
        "name": "Barbie",
        "img": " ",
        "gender": "female",
        "age": "?",
        "eye_color": "blue",
        "hair_color": "blond",
        "specie": "Human",

        "id": "",
        "name": "Ken",
        "img": " ",
        "gender": "male",
        "age": "26",
        "eye_color": "blue ",
        "hair_color": " blond",
        "specie": "Human",


      }
    
      

      {
        "id": " ",
        "title": "Barbie y el cascanueces",
        "description": "La historia trata sobre el nuevo juguete de la joven Marie Stahlbaum, el Cascanueces, recibido la noche de Navidad que cobra vida y, después de derrotar al Rey Ratón tras una dura batalla, la lleva a un reino mágico poblado por muñecos. Variedad de las tradicionales figuras de cascanueces.",
        "director": "Owen Hurley",
        "producer": "Jesyca Durchin y Jennifer Twiner McCaron",
        "poster": "",
    
        "release_date": "2001",
        "duration": "1h 20",
        "people":

        
          "id": "",
          "name": "Clara",
          "img": "17 ",
          "gender": "female",
          "age": "?",
          "eye_color": "blue",
          "hair_color": "blond",
          "specie": "Human",

          "id": "",
          "name": "cascanueces",
          "img": " ",
          "gender": "male",
          "age": "23",
          "eye_color": "blue ",
          "hair_color": " white",
          "specie": "cascanueces",


        }

      

      
        {
        "id":"",
        "title": "Barbie rapunzel",
        "description": "Trama. Barbie le cuenta una historia de la princesa Rapunzel a su hermana pequeña Kelly, que no tiene confianza en sus habilidades para pintar. Rapunzel vive como sirviente de la malvada bruja Gothel, que reside en una mansión aislada en el bosque, y crece creyendo que Gothel la salvó del abandono cuando era un bebé.",
        "director": "Owen Hurley",
        "producer": "Jesyca Durchin y Jennifer Twiner ",
        "poster": 
         "",
        "release_date": "2002",
        "duration": "1h 20",
        "people":

        
          "id": "",
          "name": "Rapuncel",
          "img": " ",
          "gender": "female",
          "age": "17",
          "eye_color": "blue",
          "hair_color": "blond",
          "specie": "Human",
  
          "id": "",
          "name": "principe Stefan",
          "img": " ",
          "gender": "male",
          "age": "20",
          "eye_color": "blue ",
          "hair_color": " bromw",
          "specie": "Human",
  
        }
        {
        "id":"",
        "title": "Barbie el lago de los cisnes",
        "description": " La historia comienza con Odette bailando en la panadería de su padre, el panadero. Un unicornio llamada Lila llega a la aldea, logra escapar de los cazadores y corre hacia un bosque encantado con Odette pisándole los talones.",
        "director": " Owen Hurley",
        "producer": "Jesyca Durchin y Jennifer Twiner ",
        "poster": 
         "",
        "release_date": " 2003",
        "duration": "1h 20 ",
        "people":

        
          "id": " ",
          "name": "Odette ",
          "img": " ",
          "gender": "female",
          "age": "17",
          "eye_color": "blue",
          "hair_color": "blond",
          "specie": "Human",
  
          "id": "",
          "name": "principe Daniel",
          "img": " ",
          "gender": "male",
          "age": "20",
          "eye_color": "blue ",
          "hair_color": " bromw",
          "specie": "Human",
  
  
        }


        {
        "id":"",
        "title": "Barbie, la princesa y la plebeya",
        "description": "Un día, las dos se encuentran en el pueblo y descubren que solamente tienen dos pequeñas diferencias: su cabello y una marca de nacimiento real que Anneliese tiene en el hombro. Pero allí comienza una aventura mágica. El profesor de Anneliese, Julian, quien está muy enamorado de ella, aunque se mantiene callado, ve que está muy presionada por su próxima boda, y entonces la lleva al pueblo, algo que siempre ha deseado. Anneliese entonces conoce a Erika, y su gata Serafina conoce al gato de Erika, Wolfie.",
        "director": "William Lau",
        "producer": "Jesyca Durchin y Jennifer Twiner ",
        "poster": 
         "",
        "release_date": " 2004",
        "duration": "1h 25 ",
        "people":

        
          "id": " ",
          "name": "Princesa Anneliese",
          "img": " ",
          "gender": "female",
          "age": "17",
          "eye_color": "blue",
          "hair_color": "blond",
          "specie": "Human",
  
          "id": "",
          "name": "Erika",
          "img": " ",
          "gender": "female",
          "age": "17",
          "eye_color": "blue ",
          "hair_color": " bromw",
          "specie": "Human",
  
  
        }

        {

        "id":"",
        "title": "Barbie Fairytopia",
        "description": "Elina (Barbie) es un hada que vive en un mundo llamado Fairytopia, hogar de todas las hadas del mundo, sin embargo y por una razón desconocida, ella no tiene alas y sufre por no poder volar. Todo esto cambia cuando su hogar se ve afectado por una misteriosa enfermedad que incapacita a todos los seres voladores, siendo obviamente ella la única inmune. Pronto se descubre que la malvada Laverna, hermana gemela de la Reina de Fairytopia, es la responsable de esto .",
        "director": "Walter P y William Lau",
        "producer": "Nancy Bennett y Luke Carroll",
        "poster": 
         "",
        "release_date": " 2005",
        "duration": "1h 29 ",
        "people":

        {
          "id": " ",
          "name": "Elina",
          "img": " ",
          "gender": "female",
          "age": "17",
          "eye_color": "blue",
          "hair_color": "blond",
          "specie": "Human",
  
          "id": "",
          "name": "Bibble",
          "img": " ",
          "gender": "Male",
          "age": "?",
          "eye_color": "blue ",
          "hair_color": "sky blue",
          "specie": "?",
  
  
        }

        
        "id":"",
        "title": "Barbie y la magia de pegaso",
        "description": "En un reino mágico, la Reina quiere sorprender a su hija, la princesa Annika, con un regalo de cumpleaños. Cuando ella abre la puerta del cuarto de Annika, descubre que Annika no se encuentra, después de haber ido a una pista de hielo sin pedir permiso. Fuera patinando, Annika conoce a un pequeño oso polar al que llama Shiver. Cuando Annika regresa al palacio, sus padres están tan preocupados que le prohíben patinar nunca más .",
        "director": "Greg Richardson",
        "producer": "Luke Carroll, Jesyca C.Durchin",
        "poster": 
         "",
        "release_date": " 2005",
        "duration": "1h 25 ",
        "people":

        {
          "id": " ",
          "name": "Princesa Annika",
          "img": " ",
          "gender": "female",
          "age": "17",
          "eye_color": "blue",
          "hair_color": "blond",
          "specie": "Human",
  
          "id": "",
          "name": "Princesa Brietta",
          "img": " ",
          "gender": "female",
          "age": "?",
          "eye_color": "blue ",
          "hair_color": "bromw",
          "specie": "?",
  
  
        }


       
        "id":"",
        "title": "Barbie fairytopia mermaidia ",
        "description":" La trama de esta película comienza poco después de los acontecimientos de la primera película, con Elina volando por el aire que todavía no puede creer que tiene alas. Pronto, Elina sabe de una joven mariposa del mar que su amigo Nalu, el príncipe tritón, ha sido secuestrado por varios hongos de Laverna, en la Ensenada de Cristal. La desterrada Laverna está buscando La Baya de la Inmunidad, una baya que causa que el que la coma sea inmune a toda magia.",
        "director": "Walter P.William Lau y Martishius",
        "producer": "Jesyca C. Durchin y Jennifer Twinner",
        "poster": 
         "",
        "release_date": " 2006",
        "duration": "1h 25 ",
        "people":

        {
          "id": " ",
          "name": "Elina ",
          "img": " ",
          "gender": "female",
          "age": "17",
          "eye_color": "blue",
          "hair_color": "blond",
          "specie": "Human",
  
          "id": "",
          "name": " Bibble",
          "img": " ",
          "gender": "male",
          "age": "?",
          "eye_color": "blue ",
          "hair_color": "sky blue",
          "specie": "?",
  
  
        }

        
        "id":"",
        "title": "Los diarios de Barbie",
        "description":"Barbie es retratada como una típica adolescente estadounidense de segundo año de secundaria que se enfrenta a los problemas que suelen afrontar los adolescentes de la vida real: hacer nuevos amigos, tener citas, cotillear e involucrarse en actividades escolares. Siempre es derrotada en todo por Raquelle, una chica snob que solía ser su mejor amiga en quinto grado.",
        "director": "Eric Fogel y Kallen Kagen",
        "producer": "Kallan Kagan",
        "poster": 
         "",
        "release_date": " 2006",
        "duration": "1h 10 ",
        "people":

        {
          "id": " ",
          "name": "Barbie ",
          "img": " ",
          "gender": "female",
          "age": "17",
          "eye_color": "blue",
          "hair_color": "blond",
          "specie": "Human",
  
          "id": "",
          "name":"Courtney",
          "img": " ",
          "gender": "female",
          "age": "?",
          "eye_color": "bromw ",
          "hair_color": "black",
          "specie": "?",
  
  
        }

        "id":"",
        "title": " Barbie y las 12 princesas bailarinas",
        "description":" La Princesa Genevieve vive en un maravilloso reino con sus 11 hermanas. Las 12 princesas son conocidas por ser muy desordenadas, por lo cual los demás reinos las evitan; su padre, el rey le pide ayuda a su prima la Duquesa Rowena para que las eduque, pero lo que el rey no sabe es que ella solo quiere su corona para convertirse en reina; para ello, comienza envenenándolo con un té.",
        "director": "Greg Richardson",
        "producer": "Shea Wageman",
        "poster": 
         "",
        "release_date": " 2006",
        "duration": "1h 21 ",
        "people":

        {
          "id": " ",
          "name": "Genevieve",
          "img": " ",
          "gender": "female",
          "age": "17",
          "eye_color": "blue",
          "hair_color": "blond",
          "specie": "Human",
  
          "id": "",
          "name":"king Randolph",
          "img": " ",
          "gender": "male",
          "age": "50",
          "eye_color": "blue",
          "hair_color": "blond",
          "specie": "?",
  
  
        }

        "id":"",
        "title": " Barbie Fairytopia: La Magia del Arco Iris",
        "description":"Siguiendo a las películas Fairytopia, Elina y su amigo Bibble, viven en la Pradera Mágica, una región en Fairytopia. Un día reciben la visita de Azura, una de las siete hadas guardianas de Fairytopia. La encantadora, gobernante de Fairytopia, ha dado instrucciones a los siete guardianes de nombrar a un aprendiz cada uno, y Azura quiere que Elina sea su aprendiz. .",
        "director": "William Lau",
        "producer": "Nancy Bennett y Luke Carroll",
        "poster": 
         "",
        "release_date": " 2007",
        "duration": "1h 12 ",
        "people":

        {
          "id": " ",
          "name": "Elina ",
          "img": " ",
          "gender": "female",
          "age": "17",
          "eye_color": "blue",
          "hair_color": "blond",
          "specie": "Human",
  
          "id": "",
          "name": " Bibble",
          "img": " ",
          "gender": "male",
          "age": "?",
          "eye_color": "blue ",
          "hair_color": "sky blue",
          "specie": "?",
  
        }

        "id":"",
        "title": " Barbie,Princesa de la isla",
        "description":" La historia se centra en Ro, una valiente y hermosa chica huérfana que naufragó en una isla tropical cuando era muy pequeña y que fue criada por varios animales: Sagi, un panda rojo sabio, Azul, un pavo real extravagante y Tika, una bebé elefante por lo que ella desarrolla la habilidad de hablar con los animales. Sin embargo, no recuerda nada de su pasado antes del naufragio y su única pista son un cofre lleno de pertenencias con una placa rota (Ro. Por lo que los animales deciden llamarla así) y una bandera de tiras con una rosa blanca.",
        "director": "Greg Richardson",
        "guion": "Cliff Ruby y Elana Lesser",
        "poster": 
         "",
        "release_date": " 2007",
        "duration": "1h 25 ",
        "people":

        {
          "id": " ",
          "name": "Ro ",
          "img": " ",
          "gender": "female",
          "age": "17",
          "eye_color": "blue",
          "hair_color": "blond",
          "specie": "Human",
  
          "id": "",
          "name": "Principe Antonio ",
          "img": " ",
          "gender": "male",
          "age": "?",
          "eye_color": "bromw",
          "hair_color": "bromw",
          "specie": "?",
  
        }

        "id":"",
        "title": "Barbie Mariposa ",
        "description":"Elina, la heroína de las películas Fairytopía le cuenta a su amigo Bibble la historia de El País de la Luz, un reino lejano poblado por hadas con alas de mariposa. Henna, la malvada hada mariposa ha envenenado a la reina de El País de la Luz en un intento de apoderarse del reino. Debido a esto, las luces de la protección de Flutterfield están en peligro de salir. Estas luces protegen El País de la Luz de los "Skeezites", monstruos que comen las hadas mariposa, y están conectados con la vida de la reina de El País de la Luz.",
        "director": "Conrad Helten",
        "guion": "Nancy Bennett y Luke Carroll",
        "poster": 
         "",
        "release_date": " 2008",
        "duration": "1h 15 ",
        "people":[

        {
          "id": " ",
          "name": "Mariposa",
          "img": " ",
          "gender": "female",
          "age": "17",
          "eye_color": "blue",
          "hair_color": "blond",
          "specie": "Hada",
        },

         {
          "id": "",
          "name": " Bibble",
          "img": " ",
          "gender": "male",
          "age": "?",
          "eye_color": "blue ",
          "hair_color": "sky blue",
          "specie": "?",
  
        }
      ]

  }

        

        "id":"",
        "title": " Barbie y el castillo de diamantes",
        "description":" Barbie y su mejor amiga Teresa, se encuentran escribiendo y cantando una canción. Sin embargo, Stacie, la hermana pequeña de Barbie, llega molesta al haber peleado con su mejor amiga, Courtney, diciendo que no vale tener amigas ya que traicionan en el momento que más importa su apoyo. Al oír esto, Barbie decide contarle un cuento sobre el valor de la amistad y como ésta puede hacer grandes cosas.",
        "director": "Gino Nichele",
        "guion": "Nancy Bennett y Luke",
        "poster": 
         "",
        "release_date": " 2008",
        "duration": "1h 19 ",
        },
        

        {
          "id": " ",
          "name": "Princesa Liana",
          "img": " ",
          "gender": "female",
          "age": "17",
          "eye_color": "blue",
          "hair_color": "blond",
          "specie": "Hada",
  
        },

        {
          "id": "",
          "name": "Princesa Alexa",
          "img": " ",
          "gender": "male",
          "age": "17",
          "eye_color": "blue ",
          "hair_color": "bromw",
          "specie": "human",
  
        },
      ]
        {
        "id":"",
        "title": " Barbie en un cuento de navidad",
        "description":"En Nochebuena, Kelly no quiere ir a un baile de la víspera de Navidad, así que Barbie le cuenta la historia de Eden Starling, una glamurosa cantante en la Inglaterra victoriana y propietaria de un teatro. Sin embargo, Eden es egoísta y solo se quiere a sí misma. Disfruta de la compañía de su presumido gato, Chuzzlewit .",
        "director": "William Lau",
        "guion": "Anita lee",
        "poster":"",
        "release_date": " 2008",
        "people":[

        {
          "id": " ",
          "name": "Barbie",
          "img": " ",
          "gender": "female",
          "age": "18",
          "eye_color": "blue",
          "hair_color": "blond",
          "specie": "Hada",
          
        },

        {
         
          "id": "",
          "name": "kelly",
          "img": " ",
          "gender": "male",
          "age": "?",
          "eye_color": "blue ",
          "hair_color": "bromw",
          "specie": "?",
  
        }
     ]

    }

       {
        "title":"Barbie escuela de princesas", 
        "description":"Bleer tendrá que aprender a ser una princesa para poder graduarse. Con la ayuda de sus amigas y un poco de magia, Bleer aprenderá a que, una princesa no solo tiene que ser hermosa, sino que tiene que tener: ¡actitud, valor y mucha confianza!", 
        "Dirección" :"Ezekiel Norton",
        "Productora": "Co-production Estados Unidos-Canadá; Barbie Entertainment, Rainmaker Entertainment",
        "Año":"2011",
        "people":[

        
          {
            "id": " ",
            "name": "Barbie",
            "img": " ",
            "gender": "female",
            "age": "18",
            "eye_color": "blue",
            "hair_color": "blond",
            "specie": "Human",
            
          },

          {
            "id": " ",
            "name": "Hadley",
            "img": " ",
            "gender": "female",
            "age": "18",
            "eye_color": "green",
            "hair_color": "bronw",
            "specie": "Human",
            
          }

        ]

       }

     {
          "title":"Barbie una navidad perfecta", 
          "description":"Los planes de vacaciones de Barbie y sus hermanas Skipper, Stacie y Chelsea se tuercen cuando el avión en el que viajan se desvía debido a una tormenta de nieve. Lejos de su Nueva York soñado, las cuatro chicas recalan en el pueblo de Tannebaun. Allí, hacen nuevos amigos y utilizan su talento para ofrecer una función a los habitantes de la pequeña localidad,
        "Dirección":"Gabriela cárdenas" ,
        "Productora":"Eduardo Giaccardi",
        "Año":"2011",
        "people":[



          {
            "id": " ",
            "name": "Barbie",
            "img": " ",
            "gender": "female",
            "age": "18",
            "eye_color": "blue",
            "hair_color": "blond",
            "specie": "Human",
            
          },

          {
            "id": " ",
            "name": "Staice",
            "img": " ",
            "gender": "female",
            "age": "18",
            "eye_color": "green",
            "hair_color": "blond",
            "specie": "Human",
            
          },
          {
          "id": " ",
          "name": "Skipper",
          "img": " ",
          "gender": "female",
          "age": "18",
          "eye_color": "green",
          "hair_color": "brown",
          "specie": "Human",
          }
        
        ]
    }



    {

        
        "title":"Barbie una aventura de sirenas ",
        "description":"Merliah Summers, la princesa sirena de Oceana, irá a Australia con sus amigos para participar en la competición de surf más prestigiosa. Sin embargo, cuando la pérfida Eris intenta tomar posesión de su trono, regresará bajo el agua para evitarlo.",
      "Dirección":"Adam L. Wood",
        "Productora":"Anita Lee",
        "Año":"2010",
        "people":[


          {
            "id": " ",
            "name": "Merlina",
            "img": " ",
            "gender": "female",
            "age": "18",
            "eye_color": "blue",
            "hair_color": "blond",
            "specie": "Siren",
            
          },

          {
            "id": " ",
            "name": "Calisa",
            "img": " ",
            "gender": "female",
            "age": "18",
            "eye_color": "green",
            "hair_color": "blond",
            "specie": "Siren",
            
          },
          {
          "id": " ",
          "name": "Zuma",
          "img": " ",
          "gender": "female",
          "age": "18",
          "eye_color": "green",
          "hair_color": "pink",
          "specie": "dolphine",
          }
        ]
    }
          "title":"Babie y las zapatillas mágicas",
          "description":"Kristyn y Hailey son llevadas a un mundo mágico del ballet gobernado por una malvada Reina de la Nieve. Las dos bailarinas bailan en sus ballet favoritos para derrotar a la reina y hacer que sus sueños se hagan realidad",
        "Dirección":"Owen hurley",
        "Productora":"mattel",
        "Año":"2013",
        "people":[

        


          {
            "id": " ",
            "name": "Kristin",
            "img": " ",
            "gender": "female",
            "age": "18",
            "eye_color": "blue",
            "hair_color": "blond",
            "specie": "Siren",
            
          },

          {
            "id": " ",
            "name": "Giselle",
            "img": " ",
            "gender": "female",
            "age": "18",
            "eye_color": "green",
            "hair_color": "brown",
            "specie": "Siren",
            
          },
          {
          "id": " ",
          "name": "Zuma",
          "img": " ",
          "gender": "female",
          "age": "18",
          "eye_color": "green",
          "hair_color": "pink",
          "specie": "dolphine",
          }
        ]
    }
       
              
        
        
        "id": "película "
              "title": " Barbie , la princesa y la estrella de pop ",
              "description": " Tori, una princesa cansada de la vida en la corte, y que sueña con ser una estrella de la música, se cambia de lugar con Keira, una cantante parecida a ella que desea saber cómo es la vida de la realeza.",
              "director": " Ezekiel Norton",
              "producer": "Shelley tabbut ",
              "release_date": " 2012",
              "people": [
                {
                  "id": " ",
                  "name": " Tori",
                  "img": " ",
                  "gender": " female",
                  "age": " 17",
                  "eye_color": " blue",
                  "hair_color": " blond",
                  "specie": "Human"
                },
         "id": "película "
              "title": " Barbie mariposa y la princesa de las hadas",
              "description": " .Mariposa se convierte en la embajadora real de Flutterfield y es enviada a hacer la paz con las Hadas de Cristal de Shimmervale. Debido a un malentendido, ella es desterrada cuando descubre los planes de una hada sombría.",
              "director": " Pedro D'Aguillón Jr.",
              "producer": " Shelley tabbut ",
              "release_date": "2013 ",
              "people": [
                {
                  "id": "  ",
                  "name": " Mariposa",
                  "img": " ",
                  "gender": " female",
                  "age": " 17",
                  "eye_color": " brown",
                  "hair_color": " blond",
                  "specie": "Human"
                },
                
               {
                  "id": " ",
                   "name": " zee ",
          "img": " ",
          "gender": " female",
          "age": " ?",
          "eye_color": " blue",
          "hair_color": " pink",
          "specie": "?"
        },
        
        {
          "id": " ",
          "name": " princesa catania ",
          "img": " ",
          "gender": " female",
          "age": " 18",
          "eye_color": " blue",
          "hair_color": " blond",
          "specie": "Human"
          "name": " zee ",
          "img": " ",
          "gender": " female",
          "age": " ?",
          "eye_color": " blue",
          "hair_color": " pink",
          "specie": "?"
        },
        
        {
          "id": " ",
          "name": " princesa catania ",
          "img": " ",
          "gender": " female",
          "age": " 18",
          "eye_color": " blue",
          "hair_color": " blond",
          "specie": "Human"
        },
        "id": "película "
      "title": " Barbie y sus hermanas en una aventurade caballos",
      "description": " Barbie y sus hermanas se embarcan en una aventura suiza hacia los majestuosos Alpes, ansiosas por pasar un fabuloso verano en una escuela de equitación. Cuando Barbie descubre en el bosque a un misterioso caballo salvaje, su viaje se convierte en algo verdaderamente mágico.",
      "director": " kyran kelly ",
      "producer": "Michelle cogan ",
      "release_date": "2013 ",
      "people": [
        {
          "id": " ",
          "name": " barbie",
          "img": " ",
          "gender": "female ",
          "age": "17 ",
          "eye_color": " blue",
          "hair_color": " blond",
          "specie": "Human"
        },

        {
          "id": " ",
          "name": " Skipper ",
          "img": " ",
          "gender": " female",
          "age": " 16",
          "eye_color": " blue",
          "hair_color": " brown",
          "specie": "Human"
        },
        {
          "id": " ",
          "name": " Staice ",
          "img": " ",
          "gender": " female",
          "age": " 14",
          "eye_color": " blue",
          "hair_color": " blond",
          "specie": "Human"
        },

      ]
{
        "id": "película "
      "title": "Barbie y la princesa de perlas ",
      "description": "Barbie es Lumina, una sirena que sueña con convertirse en princesa. Desde siempre ha tenido un poder mágico con el que puede hacer que las perlas bailen y brillen.

    "director": " Ezekiel Norton ",
      "producer": " Shawn McCorkindale",
      "release_date": " 2014",
      "people": [
        {
          "id": " ",
          "name": " princesa lumina ",
          "img": " ",
          "gender": " female",
          "age": "17 ",
          "eye_color": " blue",
          "hair_color": " blond ",
          "specie": "Human"
        },
        
        {
          "id": " ",
          "name": " príncipe delfin ",
          "img": " ",
          "gender": " Male",
          "age": " 18",
          "eye_color": " blue",
          "hair_color": " blond",
          "specie": "Human"
        },
        
        {
          "id": " ",
          "name": " caligo ",
          "img": " ",
          "gender": " Male ",
          "age": " 30",
          "eye_color": " brown",
          "hair_color": " black",
          "specie": "Human"
        },
      ]
      }

        "id": "película "
      "title": " Barbie y la puerta secreta ",
      "description": "En esta mágica aventura musical, Barbie interpretará a Alexa, una princesa tímida que prefiere leer que realizar sus deberes reales. Mientras camina por el jardín real, Alexa descubre una puerta secreta en su reino, al igual que el que está en el libro que estaba leyendo, da un paso a través de la puerta y entra en una tierra caprichosa llena de criaturas mágicas y muchas sorpresas.",
      "director": "Karen J. Lloyd. ",
      "producer": " Shelley tabbut ",
      "release_date": " 2014",
      "people": [
        {
          "id": " ",
          "name": " Princesa alexa",
          "img": " ",
          "gender": " female",
          "age": " 17",
          "eye_color": " blue",
          "hair_color": " blond",
          "specie": "Human"
        },
        
        {
          "id": " ",
          "name": " Nori ",
          "img": " ",
          "gender": " female",
          "age": " 18",
          "eye_color": " brown",
          "hair_color": " brown",
          "specie": "Human"
        },
        
        {
          "id": " ",
          "name": " Ronny ",
          "img": " ",
          "gender": " female",
          "age": " 18",
          "eye_color": " brown",
          "hair_color": " blond",
          "specie": "Human"
        },
{
        "id": "película "
      "title": " Barbie súper princesa",
      "description": " Barbie es Kara, una princesa muy actual con una vida muy normal. Un día, tras ser besada por una mariposa mágica, Kara descubre que tiene unos increíbles súper poderes que le permiten transformarse en Súper Destello, su alter ego secreto que combate el crimen y vuela por todo el reino salvando a la gente.

      "director": " Ezekiel "Zeke" Norton.",
      "producer": " Shelley tabbut ",
      "release_date": " 2015 ",
      "people": [
        {
          "id": " ",
          "name": " princesa kara ",
          "img": " ",
          "gender": "female ",
          "age": " 17 ",
          "eye_color": "blue ",
          "hair_color": " blond",
          "specie": "Human"
        },

        {
          "id": " ",
          "name": " princesa corinne",
          "img": " ",
          "gender": " female",
          "age": " 18 ",
          "eye_color": " green",
          "hair_color": " brown",
          "specie": "Human "
        },
        
        {
          "id": " ",
          "name": " Maddison ",
          "img": " ",
          "gender": "female ",
          "age": "17 ",
          "eye_color": "blue ",
          "hair_color": " purple ",
          "specie": "Human"
        },

      ]

    }


 {"id": "película "
      "title": " Barbie el campamento de princesas ",
      "description": " La princesa Courtney y Erica una famosa estrella del rock son enviadas por error a campamentos muy diferentes, Courtney al Camp Rock y Erika al Camp Royalty. Ambas, aprenderán a moverse en diferentes mundos y a demostrar que todo es posible.",
      "director": " Karen J .Lloyd",
      "producer": " Shelley tabbut ",
      "release_date": " 2015",
      "people": [
        {
          "id": " ",
          "name": " Princesa courtney",
          "img": " ",
          "gender": "female ",
          "age": "17 ",
          "eye_color": " blue",
          "hair_color": " blond",
          "specie": "Human"
        },

        {
          "id": " ",
          "name": " Erika juno ",
          "img": " ",
          "gender": " female",
          "age": " 18",
          "eye_color": " brown ",
          "hair_color": " brown",
          "specie": "Human"
        },
        
        {
          "id": " ",
          "name": " Rayna ",
          "img": " ",
          "gender": " female",
          "age": " 18",
          "eye_color": " brown",
          "hair_color": " orange",
          "specie": "Human"
        },


      ]

 }

 {
 "id": "película "
      "title": " Barbie y sus hermanas en una aventura de perritos",
      "description": " Barbie, sus hermanas y sus nuevos adorables cachorros descubren un antiguo mapa que creen que les llevará a un tesoro enterrado.",
      "director": " Andrew tan",
      "producer": " ?",
      "people": [
        {
          "id": " ",
          "name": " Barbie ",
          "img": " ",
          "gender": " female ",
          "age": " 18",
          "eye_color": " blue",
          "hair_color": " blond",
          "specie": "Human"
        },

        {
          "id": " ",
          "name": " chelsea ",
          "img": " ",
          "gender": " female",
          "age": " 8",
          "eye_color": " blue",
          "hair_color": " blond",
          "specie": "Human"
        },
        

        {
          "id": " ",
          "name": " Skipper",
          "img": " ",
          "gender": " female",
          "age": " 16",
          "eye_color": " brown",
          "hair_color": " blue",
          "specie": "Human"
        },


      ]

 }

 {
 "id": "película "
      "title": " Barbie escuadrón secreto",
      "description": " Barbie, sus amigas Teresa y Renée y sus robo-mascotas persiguen a un ladrón de joyas muy sofisticado. Sin embargo, el talento para las acrobacias de las chicas y su ingenio le pondrán las cosas muy complicadas al malhechor",
      "director": " Conrad Helten ",
      "producer": " Greta Gerwig ",
      "release_date": " 2016",
      "people": [
        {
          "id": " ",
          "name": " Barbie",
          "img": " ",
          "gender": " female",
          "age": "18 ",
          "eye_color": " blue",
          "hair_color": "blond ",
          "specie": "Human"
        },

        {
          "id": " ",
          "name": " Renne ",
          "img": " ",
          "gender": " female",
          "age": " 18",
          "eye_color": " brown",
          "hair_color": " brown",
          "specie": "Human"
        },
        
        {
          "id": " ",
          "name": "Teresa ",
          "img": " ",
          "gender": " female",
          "age": " 18",
          "eye_color": "brown ",
          "hair_color": " brown",
          "specie": "Human"
        },

      ]

    }

    {
      "id": "película "
      "title": " Barbie en una aventura espacial ",
      "description": "La vida despreocupada que Barbie lleva en su planeta se ve amenazada cuando la muñeca descubre que el brillo de la galaxia está desapareciendo; cuando percibe que las estrellas paran de moverse, viaja al Planeta Capital para investigar. ",
      "director": " Andrew tan",
      "producer": " ?",
      "release_date": " 2016",
      "people": [
        {
          "id": " ",
          "name": " Barbie",
          "img": " ",
          "gender": "female ",
          "age": " 17",
          "eye_color": " blue",
          "hair_color": " blond",
          "specie": "Human"
        },

        {
          "id": " ",
          "name": " Sal-lee ",
          "img": " ",
          "gender": " female",
          "age": " 17",
          "eye_color": " brown",
          "hair_color": " purple",
          "specie": "Human"
        },

         {
          "id": " ",
          "name": " Shena ",
          "img": " ",
          "gender": " female",
          "age": " 18",
          "eye_color": " brown",
          "hair_color": " pink",
          "specie": "Human"
        },



      ]


    }
   
   
   { "id": "película "
      "title": " Barbie y sus hermanasen la búsqueda de perritos",
      "description": "Barbie y sus hermanas Skipper, Stacie y Chelsea quieren pasar unas tranquilas vacaciones en Hawai con sus mascotas, los perritos Taffy, DJ, Rookie y Honey. No obstante, no podrán disfrutar de la tranquilidad durante mucho tiempo ya que los cachorros serán secuestrados por unos malvados y ellas deberán ir en su busca. ",
      "director": " Conrad Helten",
      "producer": "? ",
      "release_date": "2016 ",
      "people": [
        {
          "id": " ",
          "name": " barbie",
          "img": " ",
          "gender": "18 ",
          "age": " ",
          "eye_color": "blue ",
          "hair_color": " blond",
          "specie": "Human"
        },

        {
          "id": " ",
          "name": " Skipper",
          "img": " ",
          "gender": " female",
          "age": " 16",
          "eye_color": " blue",
          "hair_color": " brown",
          "specie": "Human"
        },

        {
          "id": " ",
          "name": " Stacie ",
          "img": " ",
          "gender": " female",
          "age": " 13",
          "eye_color": " blue",
          "hair_color": " blond",
          "specie": "Human"
        },


      ]

   }




{   "id": "película "
      "title": " Barbie y la super heroina de los video juegos",
      "description": " Barbie entra de forma mágica en su videojuego favorito transformada en una divertida patinadora. En el juego conoce a Cutie, una amable nube que se convierte en su amiga, y Bella, la princesa patinadora.",
      "director": " Conrad Helten",
      "producer": " ?",
      "release_date": " 2017",
      "people": [
        {
          "id": " ",
          "name": "barbie ",
          "img": " ",
          "gender": " female",
          "age": " 17",
          "eye_color": "blue",
          "hair_color": " blond",
          "specie": "Human"
        },

        {
          "id": " ",
          "name": " Cutie  ",
          "img": " ",
          "gender": " Male",
          "age": " ?",
          "eye_color": " black",
          "hair_color": " white",
          "specie": "nube"
        },

        {
          "id": " ",
          "name": " Princesa bella ",
          "img": " ",
          "gender": " female",
          "age": " 18",
          "eye_color": " purple",
          "hair_color": " purple",
          "specie": "Human"
        },

      ]

}
 "id": "película "
      "title": " barbie y los delfines mágicos",
      "description": " Barbie y sus hermanas visitan a Ken, que está trabajando en un arrecife de coral estudiando el mundo marino y a los delfines. Allí conocen a Isla, una amiga especial con un gran secreto, está tratando de salvar al delfín que tienen en el arrecife.",
      "director": " Conrad Helten",
      "producer": "? ",
      "release_date": "2017 ",
      "people": [
        {
          "id": " ",
          "name": "  barbie",
          "img": " ",
          "gender": "female ",
          "age": "18 ",
          "eye_color": "blue ",
          "hair_color": " blond",
          "specie": "Human"
        },

        {
          "id": " ",
          "name": " Skipper",
          "img": " ",
          "gender": " female",
          "age": " 16",
          "eye_color": " blue",
          "hair_color": " brown",
          "specie": "Human"
        },

        {
          "id": " ",
          "name": " ken ",
          "img": " ",
          "gender": " Male",
          "age": " 18",
          "eye_color": " blue",
          "hair_color": " blond",
          "specie": "Human"
        },
 "id": "película "
      "title": "Barbie aventura de princesas  ",
      "description": " Barbie descubre lo que significa ser una princesa moderna cuando intercambia lugares con Amelia, su doble de la realeza, quien pronto se convertirá en reina y desea escapar. ¡Barbie ayuda a la joven princesa a hallar su propia voz!",
      "director": " Conrad Helten ",
      "producer": " ?",
      "release_date": "2020",
      "people": [
        {
          "id": " ",
          "name": " barbie ",
          "img": " ",
          "gender": "female ",
          "age": "18 ",
          "eye_color": " blue",
          "hair_color": " blond",
          "specie": "Human"
        },

        {
          "id": " ",
          "name": " Reina Amelia ",
          "img": " ",
          "gender": " female",
          "age": " 18",
          "eye_color": " blue",
          "hair_color": " blond",
          "specie": "Human"
        },
        
        {
          "id": " ",
          "name": " Skipper ",
          "img": " ",
          "gender": " female",
          "age": " 16",
          "eye_color": " blue",
          "hair_color": " brown",
          "specie": "Human"
        },


    

 
      ]
    }
